mkdocs_image_captions/__init__.py
mkdocs_image_captions/plugin.py
mkdocs_image_captions-0.2.2.dist-info/LICENSE
mkdocs_image_captions-0.2.2.dist-info/METADATA
mkdocs_image_captions-0.2.2.dist-info/WHEEL
mkdocs_image_captions-0.2.2.dist-info/entry_points.txt
mkdocs_image_captions-0.2.2.dist-info/RECORD
