Metadata-Version: 2.1
Name: mkdocs-image-captions
Version: 0.2.2
Summary: MkDocs plugin that added captions to images by converting markdown encoded images into <figure> elements.
License: MIT
Keywords: mkdocs
Author: Andrii Babenko
Requires-Python: >=3.7,<4.0
Classifier: Intended Audience :: Developers
Classifier: Intended Audience :: Information Technology
Classifier: License :: OSI Approved :: MIT License
Classifier: Programming Language :: Python
Classifier: Programming Language :: Python :: 3
Classifier: Programming Language :: Python :: 3.7
Classifier: Programming Language :: Python :: 3.8
Classifier: Programming Language :: Python :: 3.9
Classifier: Programming Language :: Python :: 3.10
Classifier: Programming Language :: Python :: 3.11
Classifier: Programming Language :: Python :: 3
Classifier: Programming Language :: Python :: 3.7
Requires-Dist: mkdocs (==1.4.2)
